openmss/__init__.py
openmss/main.py
open_mss-9.0.0.dist-info/AUTHORS
open_mss-9.0.0.dist-info/LICENSE
open_mss-9.0.0.dist-info/METADATA
open_mss-9.0.0.dist-info/WHEEL
open_mss-9.0.0.dist-info/entry_points.txt
open_mss-9.0.0.dist-info/top_level.txt
open_mss-9.0.0.dist-info/RECORD
