Metadata-Version: 2.2
Name: open-mss
Version: 9.0.0
Summary: A client/server application developed in the community to collaboratively create flight plans based on model data.
Maintainer-email: Reimar Bauer <rb.proj@gmail.com>
Project-URL: Homepage, https://open-mss.github.io/
Project-URL: Issues, https://github.com/Open-MSS/mss/issues
Classifier: Programming Language :: Python :: 3
Classifier: Operating System :: OS Independent
Classifier: License :: OSI Approved :: Apache Software License
Requires-Python: >=3.8
License-File: LICENSE
License-File: AUTHORS
